[{"name":"St Andrews Way, Bromley by Bow","loc":"Bromley by Bow","region":"Unknown","type":"mid_box","gia":207655,"units":7,"avgUnit":29665,"base":87.9,"allIn":120.3,"budget":24976000},{"name":"Collet Way Rev 2","loc":"Southall","region":"Unknown","type":"mli","gia":31435,"units":4,"avgUnit":7859,"base":135.0,"allIn":168.5,"budget":5297000},{"name":"Park Royal - Western Ave","loc":"Park Royal","region":"Unknown","type":"mli","gia":111640,"units":6,"avgUnit":18607,"base":110.2,"allIn":125.0,"budget":13949000},{"name":"Croydon Single Unit Rev 3","loc":"Coomber Way, Croydon","region":"Unknown","type":"mid_box","gia":54475,"units":1,"avgUnit":54475,"base":85,"allIn":102.6,"budget":5589000},{"name":"Bromley Rev 8","loc":"Bromley","region":"Unknown","type":"mli","gia":85525,"units":9,"avgUnit":9503,"base":125.2,"allIn":147.7,"budget":12630000},{"name":"Croydon Single Unit Rev 4","loc":"Coomber Way, Croydon","region":"Unknown","type":"mid_box","gia":54475,"units":1,"avgUnit":54475,"base":85,"allIn":104.8,"budget":5711000},{"name":"Austin Drive Coventry","loc":"Austin Drive, Coventry","region":"Unknown","type":"mli","gia":149805,"units":8,"avgUnit":18726,"base":70.6,"allIn":93.9,"budget":14062000},{"name":"Bromley","loc":"Bromley","region":"Unknown","type":"mli","gia":81430,"units":9,"avgUnit":9048,"base":121.9,"allIn":147.8,"budget":12033000},{"name":"Dell, Bracknell","loc":"Bracknell","region":"Unknown","type":"mid_box","gia":150950,"units":2,"avgUnit":75475,"base":81.7,"allIn":104.2,"budget":15737000},{"name":"Collet Way Rev 3 (4-Unit)","loc":"Southall","region":"Unknown","type":"mli","gia":31435,"units":4,"avgUnit":7859,"base":132.5,"allIn":182.3,"budget":5733000},{"name":"Stirling Way","loc":"Borehamwood","region":"Unknown","type":"mli","gia":50630,"units":5,"avgUnit":10126,"base":122.6,"allIn":140.8,"budget":7129000},{"name":"Bromley Rev 4","loc":"Bromley","region":"Unknown","type":"mli","gia":81430,"units":9,"avgUnit":9048,"base":121.9,"allIn":142.6,"budget":11609000},{"name":"Eastman Way - Option 02","loc":"Hemel Hempstead","region":"Unknown","type":"mid_box","gia":143880,"units":1,"avgUnit":143880,"base":68.0,"allIn":86.6,"budget":12454000},{"name":"Chesford Grange Warrington","loc":"Warrington","region":"Unknown","type":"mid_box","gia":147315,"units":2,"avgUnit":73658,"base":66.9,"allIn":81.8,"budget":12052000},{"name":"Montrose Road, Chelmsford","loc":"Chelmsford","region":"Unknown","type":"mid_box","gia":65895,"units":1,"avgUnit":65895,"base":78.0,"allIn":109.0,"budget":7182000},{"name":"Park Royal - Western Ave","loc":"Park Royal","region":"Unknown","type":"mid_box","gia":113430,"units":2,"avgUnit":56715,"base":85.2,"allIn":97.7,"budget":11078000},{"name":"Howard Way, Harlow","loc":"Harlow","region":"Unknown","type":"mid_box","gia":94804,"units":3,"avgUnit":31601,"base":79.7,"allIn":111.9,"budget":10607000},{"name":"29 Mollison Avenue","loc":"29 Mollison Avenue","region":"Unknown","type":"mli","gia":70380,"units":8,"avgUnit":8798,"base":99.2,"allIn":140.4,"budget":9883000},{"name":"Stirling Way","loc":"Borehamwood","region":"Unknown","type":"mli","gia":50630,"units":5,"avgUnit":10126,"base":122.5,"allIn":143.8,"budget":7281000},{"name":"Croydon Single Unit","loc":"Coomber Way, Croydon","region":"Unknown","type":"mid_box","gia":54475,"units":1,"avgUnit":54475,"base":82,"allIn":88.8,"budget":4839000},{"name":"Bromley Rev 7","loc":"Bromley","region":"Unknown","type":"mli","gia":81430,"units":9,"avgUnit":9048,"base":121.9,"allIn":143.1,"budget":11650000},{"name":"Bromley Rev 3","loc":"Bromley","region":"Unknown","type":"mli","gia":80920,"units":10,"avgUnit":8092,"base":121.3,"allIn":141.8,"budget":11474000},{"name":"Bromley Rev 9 (Travis Perkins)","loc":"Bromley","region":"Unknown","type":"mli","gia":58990,"units":5,"avgUnit":11798,"base":119.3,"allIn":151.3,"budget":8926000},{"name":"DHL Building, Salford","loc":"Salford","region":"Unknown","type":"mid_box","gia":114385,"units":2,"avgUnit":57192,"base":86.4,"allIn":106.2,"budget":12151000},{"name":"Bromley Rev 5 (with self storage)","loc":"Bromley","region":"Unknown","type":"mli","gia":56855,"units":4,"avgUnit":14214,"base":120,"allIn":140.5,"budget":7986000},{"name":"Croydon Single Unit Rev 2","loc":"Coomber Way, Croydon","region":"Unknown","type":"mid_box","gia":54475,"units":1,"avgUnit":54475,"base":85,"allIn":100.7,"budget":5485000},{"name":"Eastman Way","loc":"Hemel Hempstead","region":"Unknown","type":"mid_box","gia":135875,"units":1,"avgUnit":135875,"base":68.0,"allIn":85.7,"budget":11642000},{"name":"Middleton Industrial Estate","loc":"Guildford","region":"Unknown","type":"mli","gia":69120,"units":3,"avgUnit":23040,"base":104.3,"allIn":118.6,"budget":8198000},{"name":"Bromley Rev 6","loc":"Bromley","region":"Unknown","type":"mli","gia":81430,"units":9,"avgUnit":9048,"base":121.9,"allIn":141.2,"budget":11495000},{"name":"Ashley Road","loc":"St Albans","region":"Unknown","type":"mli","gia":49170,"units":6,"avgUnit":8195,"base":118,"allIn":135.9,"budget":6683000},{"name":"Stirling Way","loc":"Borehamwood","region":"Unknown","type":"mid_box","gia":50310,"units":1,"avgUnit":50310,"base":80.0,"allIn":102.6,"budget":5164000},{"name":"Stirling Way Single Unit Rev 2","loc":"Borehamwood","region":"Unknown","type":"mid_box","gia":50310,"units":1,"avgUnit":50310,"base":80.0,"allIn":108.6,"budget":5465000},{"name":"Stirling Way Rev 3","loc":"Borehamwood","region":"Unknown","type":"mid_box","gia":50310,"units":1,"avgUnit":50310,"base":80.0,"allIn":111.0,"budget":5585000},{"name":"Goldington Road","loc":"Bedford","region":"Unknown","type":"mid_box","gia":210000,"units":7,"avgUnit":30000,"base":97.7,"allIn":116.4,"budget":24445000},{"name":"Bolney Grange","loc":"Stairbridge Lane, Bolney ","region":"Unknown","type":"mid_box","gia":251811,"units":7,"avgUnit":35973,"base":92.6,"allIn":107.9,"budget":27181000},{"name":"Borehamwood","loc":"Rowley Lane, Boreham Wood","region":"Unknown","type":"mid_box","gia":116855,"units":1,"avgUnit":116855,"base":78,"allIn":98.3,"budget":11486000},{"name":"Ferndown","loc":"Ferndown, Bournemouth","region":"Unknown","type":"mid_box","gia":110663,"units":3,"avgUnit":36888,"base":116.7,"allIn":134.1,"budget":14844000},{"name":"Boehringer site","loc":"Bracknell","region":"Unknown","type":"mid_box","gia":130065,"units":2,"avgUnit":65032,"base":88.7,"allIn":105.2,"budget":13685000},{"name":"Boehringer site Rev 2","loc":"Bracknell","region":"Unknown","type":"mid_box","gia":130720,"units":3,"avgUnit":43573,"base":90.7,"allIn":112.6,"budget":14720000},{"name":"Cox Lane","loc":"Chessington","region":"Unknown","type":"mid_box","gia":91500,"units":3,"avgUnit":30500,"base":90.3,"allIn":115.2,"budget":10544000},{"name":"Chessington Base","loc":"Surrey, KT19 1SG","region":"Unknown","type":"mli","gia":93300,"units":7,"avgUnit":13329,"base":128.9,"allIn":149.2,"budget":13918000},{"name":"Croydon","loc":"Horatius Way, Croydon","region":"Unknown","type":"mli","gia":120940,"units":9,"avgUnit":13438,"base":115.6,"allIn":147.3,"budget":17816500},{"name":"Horatius Way","loc":"Croydon","region":"Unknown","type":"mli","gia":110550,"units":5,"avgUnit":22110,"base":89.1,"allIn":114.4,"budget":12646000},{"name":"Horatius Way","loc":"Croydon","region":"Unknown","type":"mli","gia":110570,"units":5,"avgUnit":22114,"base":77.5,"allIn":115.4,"budget":12764000},{"name":"Croydon","loc":"Marlowe Way","region":"Unknown","type":"mli","gia":73395,"units":5,"avgUnit":14679,"base":107.8,"allIn":126.5,"budget":9287000},{"name":"Daventry","loc":"Daventry, Northamptonshir","region":"Unknown","type":"mid_box","gia":60815,"units":1,"avgUnit":60815,"base":72.5,"allIn":110.5,"budget":6717000},{"name":"Enderby Logistics Park - EvoLake","loc":"Enderby, Leicester","region":"Unknown","type":"big_box","gia":1131200,"units":7,"avgUnit":161600,"base":59.5,"allIn":72.0,"budget":81483000},{"name":"Enderby Logistics Park - EvoLake","loc":"Enderby, Leicester","region":"Unknown","type":"big_box","gia":1131200,"units":7,"avgUnit":161600,"base":59.5,"allIn":71.7,"budget":81094000},{"name":"Enderby Logistics Park - EvoLake","loc":"Enderby, Leicester","region":"Unknown","type":"big_box","gia":1147126,"units":4,"avgUnit":286782,"base":56.1,"allIn":68.1,"budget":78103000},{"name":"29 Mollison Avenue","loc":"29 Mollison Avenue","region":"Unknown","type":"mli","gia":70380,"units":8,"avgUnit":8798,"base":94.8,"allIn":137.3,"budget":9666000},{"name":"Gaydon","loc":"Royal Leamington Spa","region":"Unknown","type":"mid_box","gia":407106,"units":6,"avgUnit":67851,"base":78.0,"allIn":95.4,"budget":38848000},{"name":"Horsecroft Lane - Site 1","loc":"Harlow","region":"Unknown","type":"mid_box","gia":88065,"units":1,"avgUnit":88065,"base":79,"allIn":100.5,"budget":8846425},{"name":"Horsecroft Lane - Site 1 - 2 units","loc":"Harlow","region":"Unknown","type":"mid_box","gia":80880,"units":2,"avgUnit":40440,"base":98.8,"allIn":122.0,"budget":9869425},{"name":"Harlow","loc":"Horsecroft Road - Site 2","region":"Unknown","type":"mid_box","gia":30330,"units":1,"avgUnit":30330,"base":110,"allIn":138.9,"budget":4212000},{"name":"Inova Park, Leicester","loc":"Leicester","region":"Unknown","type":"mid_box","gia":560873,"units":6,"avgUnit":93479,"base":67.9,"allIn":110.8,"budget":62143520},{"name":"Starwood House","loc":"Letchworth","region":"Unknown","type":"mid_box","gia":112695,"units":2,"avgUnit":56348,"base":0,"allIn":93,"budget":10521000},{"name":"Starwood House","loc":"Letchworth","region":"Unknown","type":"mid_box","gia":84760,"units":2,"avgUnit":42380,"base":83.8,"allIn":98,"budget":8296000},{"name":"Leeds Unit 1","loc":"Leeds","region":"Unknown","type":"big_box","gia":157500,"units":1,"avgUnit":157500,"base":64,"allIn":78.7,"budget":12388000},{"name":"Leeds Unit 2","loc":"Leeds","region":"Unknown","type":"mid_box","gia":53550,"units":1,"avgUnit":53550,"base":80,"allIn":97.2,"budget":5207000},{"name":"Leeds Units 1 and 2","loc":"Leeds","region":"Unknown","type":"mid_box","gia":211050,"units":2,"avgUnit":105525,"base":0,"allIn":82.1,"budget":17324000},{"name":"SKF Luton","loc":"Sundon Park Road, Luton","region":"Unknown","type":"mid_box","gia":333815,"units":5,"avgUnit":66763,"base":72.4,"allIn":81.8,"budget":27296336},{"name":"M1 Junction 21","loc":"Annesley, Nottingham - Sh","region":"Unknown","type":"big_box","gia":699675,"units":3,"avgUnit":233225,"base":57.3,"allIn":68.0,"budget":47594000},{"name":"Waxlox Road","loc":"Park Royal","region":"Unknown","type":"mli","gia":88875,"units":4,"avgUnit":22219,"base":82.7,"allIn":113.7,"budget":10109000},{"name":"Waxlox Road","loc":"Park Royal","region":"Unknown","type":"mli","gia":88875,"units":4,"avgUnit":22219,"base":96.1,"allIn":115.0,"budget":10224000},{"name":"Colthrop Lane","loc":"Thatcham","region":"Unknown","type":"mid_box","gia":70152,"units":2,"avgUnit":35076,"base":93.8,"allIn":113.7,"budget":7979000},{"name":"Colthrop Lane","loc":"Thatcham","region":"Unknown","type":"mid_box","gia":70152,"units":2,"avgUnit":35076,"base":93.8,"allIn":118.1,"budget":8287000},{"name":"Veridion Way, Thamesmead - Evo Industria","loc":"Veridion Way, Thamesmead","region":"Unknown","type":"big_box","gia":884565,"units":5,"avgUnit":176913,"base":61.9,"allIn":93.3,"budget":82569000},{"name":"Veridion Way, Thamesmead","loc":"Thamesmead","region":"Unknown","type":"mid_box","gia":838450,"units":13,"avgUnit":64496,"base":78.8,"allIn":113.7,"budget":95322035},{"name":"Tolpits Lane, Watford","loc":"Watford","region":"Unknown","type":"mid_box","gia":132165,"units":4,"avgUnit":33041,"base":88.2,"allIn":118.8,"budget":15695000},{"name":"Deer Park Rd, Wimbledon - Option 1","loc":"Wimbledon","region":"Unknown","type":"mli","gia":111415,"units":4,"avgUnit":27854,"base":96.8,"allIn":112.6,"budget":12548000},{"name":"Deer Park Rd, Wimbledon - Option 2","loc":"Wimbledon","region":"Unknown","type":"mli","gia":110755,"units":9,"avgUnit":12306,"base":97.7,"allIn":113.7,"budget":12597000},{"name":"Deer Park Rd, Wimbledon - Option 1","loc":"Wimbledon","region":"Unknown","type":"mid_box","gia":122640,"units":4,"avgUnit":30660,"base":93.7,"allIn":109.3,"budget":13403000},{"name":"Banbury","loc":"Ruscote Avenue","region":"Unknown","type":"mid_box","gia":439170,"units":13,"avgUnit":33782,"base":81.8,"allIn":100.1,"budget":43968000},{"name":"Banbury","loc":"Ruscote Avenue","region":"Unknown","type":"mid_box","gia":439170,"units":8,"avgUnit":54896,"base":81.8,"allIn":107.7,"budget":47302000},{"name":"Kings Road","loc":"Tyseley, Birmingham","region":"Unknown","type":"mli","gia":79295,"units":4,"avgUnit":19824,"base":94.1,"allIn":108.5,"budget":8606000},{"name":"Bracknell Dell","loc":"Bracknell","region":"Unknown","type":"mid_box","gia":145580,"units":2,"avgUnit":72790,"base":82.4,"allIn":105.3,"budget":15336000},{"name":"Coomber Way","loc":"Croydon","region":"Unknown","type":"mli","gia":54180,"units":4,"avgUnit":13545,"base":127.2,"allIn":150.3,"budget":8144000},{"name":"Lincoln Road, Enfield","loc":"Lincoln Road, Enfield","region":"Unknown","type":"mli","gia":110605,"units":8,"avgUnit":13826,"base":99.9,"allIn":115.8,"budget":12801600},{"name":"Gloucester Business Park","loc":"Gloucester","region":"Unknown","type":"mid_box","gia":338145,"units":11,"avgUnit":30740,"base":91.6,"allIn":110.4,"budget":37323000},{"name":"Barton Dock","loc":"Manchester","region":"Unknown","type":"mid_box","gia":177385,"units":4,"avgUnit":44346,"base":85.2,"allIn":101.8,"budget":18061000},{"name":"Bakewell Road","loc":"Peterborough","region":"Unknown","type":"mid_box","gia":131955,"units":3,"avgUnit":43985,"base":85.0,"allIn":106.4,"budget":14041000},{"name":"Britannia Road","loc":"Waltham Cross","region":"Unknown","type":"mli","gia":75870,"units":4,"avgUnit":18968,"base":96.0,"allIn":121.5,"budget":9218000},{"name":"Blackhorse Lane","loc":"Walthamstow","region":"Unknown","type":"mli","gia":162437,"units":9,"avgUnit":18049,"base":108.8,"allIn":121.3,"budget":19711000},{"name":"Blackhorse Lane","loc":"Walthamstow","region":"Unknown","type":"mli","gia":136080,"units":9,"avgUnit":15120,"base":134.5,"allIn":148.4,"budget":20197000},{"name":"Tolpits Lane","loc":"Tolpits Lane, Watford","region":"Unknown","type":"mli","gia":69850,"units":3,"avgUnit":23283,"base":105.4,"allIn":130.8,"budget":9139000},{"name":"Tolpits Lane","loc":"Tolpits Lane, Watford","region":"Unknown","type":"mli","gia":76500,"units":8,"avgUnit":9562,"base":126.4,"allIn":151.8,"budget":11613000},{"name":"Orphanage Road - Rev A","loc":"Orphanage Road, Watford","region":"Unknown","type":"mli","gia":92040,"units":5,"avgUnit":18408,"base":92.7,"allIn":116.5,"budget":10724147},{"name":"Orphanage Road","loc":"Orphanage Road, Watford","region":"Unknown","type":"mli","gia":92040,"units":5,"avgUnit":18408,"base":92.1,"allIn":116.0,"budget":10674147},{"name":"Colthrop Lane Rev 3","loc":"Thatcham","region":"Unknown","type":"mid_box","gia":77760,"units":2,"avgUnit":38880,"base":92.4,"allIn":111.2,"budget":8649000},{"name":"Colthrop Lane Rev 4","loc":"Thatcham","region":"Unknown","type":"mid_box","gia":85140,"units":1,"avgUnit":85140,"base":78,"allIn":95.6,"budget":8139000},{"name":"Colthrop Lane","loc":"Thatcham","region":"Unknown","type":"mid_box","gia":77760,"units":2,"avgUnit":38880,"base":92.4,"allIn":115.3,"budget":8967000},{"name":"Colthrop Lane","loc":"Thatcham","region":"Unknown","type":"mid_box","gia":85140,"units":1,"avgUnit":85140,"base":78,"allIn":97.8,"budget":8331000},{"name":"Colthrop Lane","loc":"Thatcham","region":"Unknown","type":"mid_box","gia":77975,"units":2,"avgUnit":38988,"base":92.3,"allIn":115.3,"budget":8987000},{"name":"EVO Industrial - Veridion Way, Thamesmea","loc":"Veridion Way, Thamesmead","region":"Unknown","type":"big_box","gia":884565,"units":5,"avgUnit":176913,"base":59.8,"allIn":96.7,"budget":85540000},{"name":"Veridion Way, Thamesmead","loc":"Thamesmead","region":"Unknown","type":"big_box","gia":884565,"units":5,"avgUnit":176913,"base":59.8,"allIn":103.9,"budget":91944000},{"name":"Veridion Way, Thamesmead","loc":"Thamesmead","region":"Unknown","type":"big_box","gia":869405,"units":5,"avgUnit":173881,"base":63.1,"allIn":95.1,"budget":82690000},{"name":"Veridion Way, Thamesmead","loc":"Thamesmead","region":"Unknown","type":"big_box","gia":1215925,"units":5,"avgUnit":243185,"base":46.8,"allIn":81.0,"budget":98490000},{"name":"Veridion Way, Thamesmead - Evo Industria","loc":"Veridion Way, Thamesmead","region":"Unknown","type":"mid_box","gia":838450,"units":13,"avgUnit":64496,"base":83.8,"allIn":119.2,"budget":99976035},{"name":"Veridion Way, Thamesmead","loc":"Thamesmead","region":"Unknown","type":"mid_box","gia":529767,"units":9,"avgUnit":58863,"base":86.1,"allIn":129.8,"budget":68765035},{"name":"Bolney Grange","loc":"Stairbridge Lane, Bolney ","region":"Unknown","type":"mli","gia":220265,"units":10,"avgUnit":22026,"base":88.9,"allIn":101.1,"budget":22271000},{"name":"Bolney Grange","loc":"Stairbridge Lane, Bolney ","region":"Unknown","type":"mli","gia":231285,"units":13,"avgUnit":17791,"base":81.3,"allIn":94.7,"budget":21904000},{"name":"Borehamwood","loc":"Rowley Lane, Borehamwood ","region":"Unknown","type":"mid_box","gia":116855,"units":1,"avgUnit":116855,"base":78,"allIn":97.9,"budget":11440000},{"name":"Borehamwood Planning Layout","loc":"Rowley Lane, Borehamwood ","region":"Unknown","type":"mid_box","gia":115314,"units":1,"avgUnit":115314,"base":75,"allIn":95.1,"budget":10963000},{"name":"Borehamwood Planning Layout","loc":"Rowley Lane, Boreham Wood","region":"Unknown","type":"mid_box","gia":115314,"units":1,"avgUnit":115314,"base":75,"allIn":95.4,"budget":10997000},{"name":"Borehamwood Planning Layout","loc":"Rowley Lane, Boreham Wood","region":"Unknown","type":"mid_box","gia":107960,"units":1,"avgUnit":107960,"base":79,"allIn":100.0,"budget":10800000},{"name":"Veridion Way, Thamesmead","loc":"Thamesmead","region":"Unknown","type":"big_box","gia":884565,"units":5,"avgUnit":176913,"base":59.8,"allIn":99.5,"budget":88013000},{"name":"Veridion Way, Thamesmead","loc":"Thamesmead","region":"Unknown","type":"big_box","gia":884565,"units":5,"avgUnit":176913,"base":59.8,"allIn":97.3,"budget":86069000},{"name":"Veridion Way, Thamesmead - Evo Industria","loc":"Veridion Way, Thamesmead","region":"Unknown","type":"big_box","gia":869405,"units":5,"avgUnit":173881,"base":62.0,"allIn":93.9,"budget":81661000},{"name":"Veridion Way, Thamesmead","loc":"Thamesmead","region":"Unknown","type":"multi_storey","gia":1873400,"units":4,"avgUnit":468350,"base":179.1,"allIn":214.5,"budget":401921000},{"name":"Veridion Way, Thamesmead","loc":"Thamesmead","region":"Unknown","type":"multi_storey","gia":1275440,"units":5,"avgUnit":255088,"base":132.0,"allIn":167.0,"budget":212949000},{"name":"Colthrop Lane","loc":"Thatcham","region":"Unknown","type":"mid_box","gia":71039,"units":2,"avgUnit":35520,"base":19,"allIn":103.8,"budget":7377000},{"name":"Bolney Grange","loc":"Stairbridge Lane, Bolney ","region":"Unknown","type":"mli","gia":220265,"units":8,"avgUnit":27533,"base":88.9,"allIn":102.1,"budget":22486000},{"name":"Bolney Grange","loc":"Stairbridge Lane, Bolney ","region":"Unknown","type":"mli","gia":231285,"units":13,"avgUnit":17791,"base":81.3,"allIn":95.6,"budget":22120000},{"name":"Enderby Logistics Park - EvoLake","loc":"Enderby, Leicester","region":"Unknown","type":"big_box","gia":1131200,"units":7,"avgUnit":161600,"base":59.5,"allIn":69.9,"budget":79089000},{"name":"Eastman Way","loc":"Hemel Hempstead","region":"Unknown","type":"mid_box","gia":128950,"units":1,"avgUnit":128950,"base":68.0,"allIn":88.3,"budget":11388000},{"name":"South Crescent","loc":"Canning Town","region":"Unknown","type":"mid_box","gia":41845,"units":1,"avgUnit":41845,"base":94.0,"allIn":112.9,"budget":4722000}]
